[
    {
        "Latitude":18.4983013343,
        "Longitude":73.8261230359,
        "Safety_Score":0.9
    },
    {
        "Latitude":18.4582227726,
        "Longitude":73.855020006,
        "Safety_Score":0.8888888889
    },
    {
        "Latitude":18.469206762,
        "Longitude":73.8641907417,
        "Safety_Score":0.9555555556
    },
    {
        "Latitude":18.5411154682,
        "Longitude":73.8830923612,
        "Safety_Score":0.6555555556
    },
    {
        "Latitude":18.5632605516,
        "Longitude":73.9326666121,
        "Safety_Score":0.0
    },
    {
        "Latitude":18.5393074186,
        "Longitude":73.8286673782,
        "Safety_Score":0.6777777778
    },
    {
        "Latitude":18.5169606325,
        "Longitude":73.8365357198,
        "Safety_Score":0.5555555556
    },
    {
        "Latitude":18.5154963936,
        "Longitude":73.8552649702,
        "Safety_Score":0.7777777778
    },
    {
        "Latitude":18.5102200062,
        "Longitude":73.9247869644,
        "Safety_Score":0.5666666667
    },
    {
        "Latitude":18.5085977176,
        "Longitude":73.8579496705,
        "Safety_Score":0.7777777778
    },
    {
        "Latitude":18.4696641372,
        "Longitude":73.8895027289,
        "Safety_Score":0.6666666667
    },
    {
        "Latitude":18.5364612117,
        "Longitude":73.8924480113,
        "Safety_Score":0.8222222222
    },
    {
        "Latitude":18.5072141783,
        "Longitude":73.8055167226,
        "Safety_Score":0.2111111111
    },
    {
        "Latitude":18.5224397066,
        "Longitude":73.8705599878,
        "Safety_Score":0.6
    },
    {
        "Latitude":18.4892270746,
        "Longitude":74.0234550544,
        "Safety_Score":0.6777777778
    },
    {
        "Latitude":18.4878067163,
        "Longitude":74.0228981908,
        "Safety_Score":0.7
    },
    {
        "Latitude":18.6269890679,
        "Longitude":74.0332042531,
        "Safety_Score":0.9555555556
    },
    {
        "Latitude":18.4874372686,
        "Longitude":73.867776072,
        "Safety_Score":0.9333333333
    },
    {
        "Latitude":18.5333919116,
        "Longitude":73.9328623091,
        "Safety_Score":0.8777777778
    },
    {
        "Latitude":18.4863053045,
        "Longitude":73.8486990525,
        "Safety_Score":1.0
    },
    {
        "Latitude":18.4755211439,
        "Longitude":73.8542255327,
        "Safety_Score":0.8444444444
    },
    {
        "Latitude":18.5204111074,
        "Longitude":73.8696131816,
        "Safety_Score":0.9555555556
    },
    {
        "Latitude":18.5302755648,
        "Longitude":73.8495246281,
        "Safety_Score":0.6111111111
    },
    {
        "Latitude":18.4540887356,
        "Longitude":73.8026080102,
        "Safety_Score":0.5
    },
    {
        "Latitude":18.5004083077,
        "Longitude":73.858987108,
        "Safety_Score":0.7555555556
    },
    {
        "Latitude":18.4627621697,
        "Longitude":73.775113047,
        "Safety_Score":1.0
    },
    {
        "Latitude":18.5677310629,
        "Longitude":73.9143326068,
        "Safety_Score":0.4111111111
    },
    {
        "Latitude":18.5139663943,
        "Longitude":73.8540521892,
        "Safety_Score":0.8222222222
    },
    {
        "Latitude":18.5725910538,
        "Longitude":73.8784973193,
        "Safety_Score":0.9222222222
    },
    {
        "Latitude":18.4856022016,
        "Longitude":73.9036146899,
        "Safety_Score":0.9666666667
    },
    {
        "Latitude":18.4755363187,
        "Longitude":73.8031326145,
        "Safety_Score":0.9333333333
    },
    {
        "Latitude":18.5456377435,
        "Longitude":73.8868294026,
        "Safety_Score":0.6555555556
    }
]